Metadata-Version: 2.1
Name: petals
Version: 2.2.0.post1
Summary: Easy way to efficiently run 100B+ language models without high-end GPUs
Home-page: https://github.com/bigscience-workshop/petals
Author: Petals Developers
Author-email: petals-devs@googlegroups.com
Project-URL: Bug Tracker, https://github.com/bigscience-workshop/petals/issues
Classifier: Development Status :: 4 - Beta
Classifier: Intended Audience :: Developers
Classifier: Intended Audience :: Science/Research
Classifier: License :: OSI Approved :: MIT License
Classifier: Programming Language :: Python :: 3
Classifier: Programming Language :: Python :: 3.8
Classifier: Programming Language :: Python :: 3.9
Classifier: Programming Language :: Python :: 3.10
Classifier: Programming Language :: Python :: 3.11
Classifier: Topic :: Scientific/Engineering
Classifier: Topic :: Scientific/Engineering :: Mathematics
Classifier: Topic :: Scientific/Engineering :: Artificial Intelligence
Classifier: Topic :: Software Development
Classifier: Topic :: Software Development :: Libraries
Classifier: Topic :: Software Development :: Libraries :: Python Modules
Requires-Python: >=3.8
License-File: LICENSE
Requires-Dist: torch >=1.12
Requires-Dist: bitsandbytes ==0.41.1
Requires-Dist: accelerate >=0.22.0
Requires-Dist: huggingface-hub <1.0.0,>=0.11.1
Requires-Dist: tokenizers >=0.13.3
Requires-Dist: transformers <4.35.0,>=4.32.0
Requires-Dist: speedtest-cli ==2.1.3
Requires-Dist: pydantic <2.0,>=1.10
Requires-Dist: hivemind ==1.1.10.post2
Requires-Dist: tensor-parallel ==1.0.23
Requires-Dist: humanfriendly
Requires-Dist: async-timeout >=4.0.2
Requires-Dist: packaging >=20.9
Requires-Dist: sentencepiece >=0.1.99
Requires-Dist: peft ==0.5.0
Requires-Dist: safetensors >=0.3.1
Requires-Dist: Dijkstar >=2.6.0
Requires-Dist: cpufeature >=0.2.0 ; platform_machine == "x86_64"
Provides-Extra: dev
Requires-Dist: pytest ==6.2.5 ; extra == 'dev'
Requires-Dist: pytest-forked ; extra == 'dev'
Requires-Dist: pytest-asyncio ==0.16.0 ; extra == 'dev'
Requires-Dist: black ==22.3.0 ; extra == 'dev'
Requires-Dist: isort ==5.10.1 ; extra == 'dev'
Requires-Dist: psutil ; extra == 'dev'
